app.py
autoboat_telemetry_server/__init__.py
autoboat_telemetry_server/lock_manager.py
autoboat_telemetry_server/models.py
autoboat_telemetry_server/types.py
autoboat_telemetry_server/routes/__init__.py
autoboat_telemetry_server/routes/autopilot_parameters.py
autoboat_telemetry_server/routes/boat_status.py
autoboat_telemetry_server/routes/instance_manager.py
autoboat_telemetry_server/routes/waypoints.py
instance/config.py
telemetry_server-4.3.1.dist-info/licenses/LICENSE
telemetry_server-4.3.1.dist-info/METADATA
telemetry_server-4.3.1.dist-info/WHEEL
telemetry_server-4.3.1.dist-info/top_level.txt
telemetry_server-4.3.1.dist-info/RECORD
