Metadata-Version: 2.4
Name: telemetry_server
Version: 4.3.1
Summary: Telemetry server for Autoboat
Project-URL: Github, https://github.com/autoboat-vt/telemetry_server
Project-URL: Documentation, https://autoboat-vt.github.io/documentation
License-File: LICENSE
Requires-Dist: Flask<4.0,>=3.1
Requires-Dist: Flask-SQLAlchemy<4.0,>=3.1
Requires-Dist: gunicorn<24.0,>=23.0
Requires-Dist: blinker<2.0,>=1.9
Requires-Dist: click<9.0,>=8.2
Requires-Dist: itsdangerous<3.0,>=2.2
Requires-Dist: Jinja2<4.0,>=3.1
Requires-Dist: MarkupSafe<4.0,>=3.0
Requires-Dist: packaging<26.0,>=25.0
Requires-Dist: SQLAlchemy<3.0,>=2.0
Requires-Dist: Werkzeug<4.0,>=3.1
Provides-Extra: dev
Requires-Dist: build<2.0,>=1.3; extra == "dev"
Requires-Dist: pyproject_hooks<2.0,>=1.2; extra == "dev"
Requires-Dist: annotated-types<1.0,>=0.7; extra == "dev"
Requires-Dist: typing_extensions<5.0,>=4.14; extra == "dev"
Requires-Dist: typing-inspection<1.0,>=0.4; extra == "dev"
Dynamic: license-file
